[
  {
    "ParameterKey": "VpcCidr",
    "ParameterValue": "10.192.0.0/16"
  },

  {
    "ParameterKey": "SubnetCidr1",
    "ParameterValue": "10.192.10.0/24"
  },
  {
    "ParameterKey": "SubnetCidr2",
    "ParameterValue": "10.192.11.0/24"
  },
  {
    "ParameterKey": "SubnetCidr3",
    "ParameterValue": "10.192.20.0/24"
  },
  {
    "ParameterKey": "region",
    "ParameterValue": "us-east-1"
  },
  {
    "ParameterKey": "Name",
    "ParameterValue": "CSYE"
  },
  {
    "ParameterKey": "ImageID",
    "ParameterValue": "ami-0794561e78628936b"
  },
  {
    "ParameterKey": "KeyName",
    "ParameterValue": "csyekeypairall"
  },
  {
    "ParameterKey": "CDS3Bucket",
    "ParameterValue": "codedeploy.shaktichetan.me"
  },
  {
    "ParameterKey": "HostedZone",
    "ParameterValue": "Z2NX4T3LPP2B35"
  },
  {
    "ParameterKey": "DNSName",
    "ParameterValue": "dev.shaktichetan.me"
  }
]
